{
    "destinations": {
        "outstation": [
            {
                "id": "tirunelveli",
                "name": "Tirunelveli",
                "price": 1800
            },
            {
                "id": "kanyakumari",
                "name": "Kanyakumari",
                "price": 3700
            },
            {
                "id": "madurai",
                "name": "Madurai",
                "price": 4500
            },
            {
                "id": "rameswaram",
                "name": "Rameswaram",
                "price": 5500
            },
            {
                "id": "courtallam",
                "name": "Courtallam",
                "price": 3600
            },
            {
                "id": "chennai",
                "name": "Chennai",
                "price": 16000
            },
            {
                "id": "coimbatore",
                "name": "Coimbatore",
                "price": 9000
            },
            {
                "id": "bangalore",
                "name": "Bangalore",
                "price": 16500
            }
        ],
        "local": [
            {
                "id": "tiruchendur",
                "name": "Tiruchendur",
                "price": 1650
            },
            {
                "id": "beach_harbour",
                "name": "Beach & Harbour",
                "price": 800
            },
            {
                "id": "city_highlights",
                "name": "City Highlights",
                "price": 1800
            }
        ],
        "college": [
            {
                "id": "kerala_tour",
                "name": "Kerala Tour Packages",
                "price": 0,
                "note": "Custom pricing based on group size"
            },
            {
                "id": "karnataka_tour",
                "name": "Karnataka Tour Packages",
                "price": 0,
                "note": "Custom pricing based on group size"
            },
            {
                "id": "industrial_visit",
                "name": "Industrial Visit (Chennai/Coimbatore)",
                "price": 15000
            }
        ]
    },
    "expenseOptions": [
        {
            "id": "food",
            "label": "Food Arrangement",
            "price": 0,
            "description": "Customizable based on preference"
        },
        {
            "id": "accommodation",
            "label": "Stay/Accommodation",
            "price": 0,
            "description": "Choice of Home stay, Hotel or 3-Star"
        }
    ]
}